twks/__init__.py
twks/client/__init__.py
twks/client/twks_client.py
twks/nanopub/__init__.py
twks/nanopub/nanopublication.py
twks_client-1.0.3.dist-info/METADATA
twks_client-1.0.3.dist-info/WHEEL
twks_client-1.0.3.dist-info/top_level.txt
twks_client-1.0.3.dist-info/RECORD
