Metadata-Version: 2.1
Name: twks-client
Version: 1.0.3
Summary: Tetherless World Knowledge Store (TWKS) client
Home-page: https://github.com/tetherless-world/twks
Author: Tetherless World Constellation
Author-email: UNKNOWN
License: Apache License 2.0
Platform: UNKNOWN
Classifier: Programming Language :: Python :: 3
Classifier: License :: OSI Approved :: Apache Software License
Classifier: Operating System :: OS Independent
Requires-Dist: rdflib (>=4)
Requires-Dist: SPARQLWrapper (<2,>=1)
Requires-Dist: requests (<3,>=2)
